access_checker/__init__.py
access_checker/acl_parser.py
access_checker/acl_parser_bk.py
access_checker/brain.py
access_checker/gui_access_checker.py
access_checker/ip_range_check.py
access_checker/main.py
access_checker/port_and_protocols.py
access_checker/wc_mask_to_cidr.py
access_checker/templates/access_page.html
access_checker/templates/result.html
access_checker_sbhalodia-1.0.3.dist-info/LICENSE
access_checker_sbhalodia-1.0.3.dist-info/METADATA
access_checker_sbhalodia-1.0.3.dist-info/WHEEL
access_checker_sbhalodia-1.0.3.dist-info/entry_points.txt
access_checker_sbhalodia-1.0.3.dist-info/top_level.txt
access_checker_sbhalodia-1.0.3.dist-info/RECORD
