Metadata-Version: 2.1
Name: access-checker-sbhalodia
Version: 1.0.3
Summary: Access checker for Cisco ACL(extended ACL)
Home-page: https://github.com/sanp2017/access-checker-sbhalodia.git
Author: Sandeep Bhalodia
Author-email: sandeeep.says@gmail.com
License: UNKNOWN
Platform: UNKNOWN
Classifier: Programming Language :: Python :: 3.7
Classifier: License :: OSI Approved :: MIT License
Classifier: Operating System :: OS Independent
Requires-Dist: flask
Requires-Dist: flask-bootstrap
